<ext id="145" cad="Brasil" sec="pol" sem="94b">
<p>
<s> Burle Filho disse que combinou a ida de seu auxiliar apOs telefonar para seu colega carioca, AntOnio Carlos Biscaia . </s>
<s> Segundo Burle Filho, Biscaia nao lhe adiantou nada por telefone sobre o assunto . </s>
</p>
<p>
<s> Queremos saber se o bicho de Sao Paulo e o do Rio sao ramificacoes de uma grande organizacao criminosa . </s>
<s> Ao mesmo tempo, estamos esperando denUncias sobre a atuacao dos bicheiros paulistas , disse Burle Filho . </s>
</p>
</ext>
